polaris_ai_datainsight/__init__.py
polaris_ai_datainsight/datainsight_extractor.py
polaris_ai_datainsight/py.typed
polaris_ai_datainsight/utils/__init__.py
polaris_ai_datainsight/utils/file_utils.py
polaris_ai_datainsight/utils/http_utils.py
polaris_ai_datainsight-1.0.0.dist-info/LICENSE
polaris_ai_datainsight-1.0.0.dist-info/METADATA
polaris_ai_datainsight-1.0.0.dist-info/WHEEL
polaris_ai_datainsight-1.0.0.dist-info/RECORD
