Metadata-Version: 2.3
Name: polaris-ai-datainsight
Version: 1.0.0
Summary: This package is Python SDK for Polaris AI DataInsight.
License: MIT
Author: Polaris Office
Author-email: ai@polarisoffice.com
Requires-Python: >=3.10,<4.0
Classifier: License :: OSI Approved :: MIT License
Classifier: Programming Language :: Python :: 3
Classifier: Programming Language :: Python :: 3.10
Classifier: Programming Language :: Python :: 3.11
Classifier: Programming Language :: Python :: 3.12
Classifier: Programming Language :: Python :: 3.13
Requires-Dist: pydantic (>=2)
Requires-Dist: python-dotenv (>=1.1.1,<2.0.0)
Requires-Dist: requests (>=2.27)
